gemnine/__init__.py
gemnine/__main__.py
gemnine/bot.py
gemnine/cli.py
gemnine/exc.py
gemnine-0.1.13.dist-info/LICENSE
gemnine-0.1.13.dist-info/METADATA
gemnine-0.1.13.dist-info/WHEEL
gemnine-0.1.13.dist-info/entry_points.txt
gemnine-0.1.13.dist-info/RECORD
