Metadata-Version: 2.1
Name: gemnine
Version: 0.1.13
Summary: Wrapper for Gemini AI API
Home-page: https://github.com/VermiIIi0n/Gemnine
License: MIT
Keywords: utilities,gemini,async,api
Author: VermiIIi0n
Author-email: dungeon.behind0t@icloud.com
Requires-Python: >=3.12,<4.0
Classifier: Development Status :: 4 - Beta
Classifier: Framework :: Pytest
Classifier: Intended Audience :: Developers
Classifier: License :: OSI Approved :: MIT License
Classifier: Operating System :: OS Independent
Classifier: Programming Language :: Python :: 3
Classifier: Programming Language :: Python :: 3.12
Classifier: Programming Language :: Python :: Implementation :: CPython
Classifier: Programming Language :: Python :: Implementation :: PyPy
Classifier: Topic :: Utilities
Classifier: Typing :: Typed
Requires-Dist: httpx[http2,socks] (>=0.26.0,<0.28.0)
Requires-Dist: pillow (>=10.2.0,<11.0.0)
Requires-Dist: platformdirs (>=4.2.0,<5.0.0)
Requires-Dist: pydantic (>=2.6.1,<3.0.0)
Requires-Dist: tiktoken (>=0.6.0,<0.7.0)
Requires-Dist: toml (>=0.10.2,<0.11.0)
Requires-Dist: ujson (>=5.9.0,<6.0.0)
Requires-Dist: vermils (>=0.3.4,<0.4.0)
Project-URL: Issues, https://github.com/VermiIIi0n/Gemnine/issues
